news_bigdata_mcp-1.0.0.dist-info/licenses/LICENSE
news_mcp_server/__init__.py
news_mcp_server/__main__.py
news_mcp_server/server.py
news_bigdata_mcp-1.0.0.dist-info/METADATA
news_bigdata_mcp-1.0.0.dist-info/WHEEL
news_bigdata_mcp-1.0.0.dist-info/entry_points.txt
news_bigdata_mcp-1.0.0.dist-info/top_level.txt
news_bigdata_mcp-1.0.0.dist-info/RECORD
