Metadata-Version: 2.4
Name: news_bigdata_mcp
Version: 1.0.0
Summary: 🔥 舆情大数据 MCP 服务 - 企业舆情监控、情感分析和新闻舆情查询
Author: handaas
License: MIT
Project-URL: Homepage, https://github.com/handaas/news-mcp-server
Project-URL: Repository, https://github.com/handaas/news-mcp-server
Project-URL: Issues, https://github.com/handaas/news-mcp-server/issues
Keywords: mcp,news,sentiment,analysis,enterprise,monitoring
Classifier: Development Status :: 4 - Beta
Classifier: Intended Audience :: Developers
Classifier: Programming Language :: Python :: 3
Classifier: Programming Language :: Python :: 3.10
Classifier: Programming Language :: Python :: 3.11
Classifier: Programming Language :: Python :: 3.12
Classifier: Operating System :: OS Independent
Classifier: Topic :: Software Development :: Libraries :: Python Modules
Requires-Python: >=3.10
License-File: LICENSE
Requires-Dist: mcp>=1.6.0
Requires-Dist: python-dotenv>=1.0.0
Requires-Dist: requests>=2.28.0
Dynamic: license-file
